hm3u8dl_cli/SeverClient.py
hm3u8dl_cli/__init__.py
hm3u8dl_cli/cli.py
hm3u8dl_cli/download.py
hm3u8dl_cli/idm.py
hm3u8dl_cli/m3u8download.py
hm3u8dl_cli/merge.py
hm3u8dl_cli/package.py
hm3u8dl_cli/processBar.py
hm3u8dl_cli/tsInfo.py
hm3u8dl_cli/util.py
hm3u8dl_cli/version.py
hm3u8dl_cli/Tools/ffmpeg.exe
hm3u8dl_cli/Tools/mp4decrypt_linux
hm3u8dl_cli/Tools/mp4decrypt_mac
hm3u8dl_cli/Tools/mp4decrypt_win.exe
hm3u8dl_cli/Tools/youkudecrypt.exe
hm3u8dl_cli/__pycache__/__init__.cpython-38.pyc
hm3u8dl_cli/__pycache__/download.cpython-38.pyc
hm3u8dl_cli/__pycache__/idm.cpython-38.pyc
hm3u8dl_cli/__pycache__/m3u8download.cpython-38.pyc
hm3u8dl_cli/__pycache__/merge.cpython-38.pyc
hm3u8dl_cli/__pycache__/processBar.cpython-38.pyc
hm3u8dl_cli/__pycache__/tsInfo.cpython-38.pyc
hm3u8dl_cli/__pycache__/util.cpython-38.pyc
hm3u8dl_cli/__pycache__/version.cpython-38.pyc
hm3u8dl_cli/decryptors/AES_128_CBC.py
hm3u8dl_cli/decryptors/AES_128_ECB.py
hm3u8dl_cli/decryptors/CHACHA.py
hm3u8dl_cli/decryptors/FakeImage.py
hm3u8dl_cli/decryptors/Widevine.py
hm3u8dl_cli/decryptors/__init__.py
hm3u8dl_cli/decryptors/copyrightDRM.py
hm3u8dl_cli/decryptors_magic/__init__.py
hm3u8dl_cli/decryptors_magic/bjcloudvod.py
hm3u8dl_cli/decryptors_magic/bokecc.py
hm3u8dl_cli/decryptors_magic/cctv.py
hm3u8dl_cli/decryptors_magic/drm_getlicense_v1.py
hm3u8dl_cli/decryptors_magic/tencent_course.py
hm3u8dl_cli/decryptors_magic/urlmagic.py
hm3u8dl_cli/decryptors_magic/xet.py
hm3u8dl_cli/internetdownloadmanager/__init__.py
hm3u8dl_cli/internetdownloadmanager/internetdownloadmanager.py
hm3u8dl_cli/internetdownloadmanager/utils.py
hm3u8dl_cli/m3u8Parser/Parser.py
hm3u8dl_cli/m3u8Parser/__init__.py
hm3u8dl_cli/m3u8Parser/download_infos.py
hm3u8dl_cli/ts_demuxer/__init__.py
hm3u8dl_cli/ts_demuxer/packet.py
hm3u8dl_cli/ts_demuxer/pat_section.py
hm3u8dl_cli/ts_demuxer/pes.py
hm3u8dl_cli/ts_demuxer/pes_stream.py
hm3u8dl_cli/ts_demuxer/pmt_section.py
hm3u8dl_cli/ts_demuxer/psi.py
hm3u8dl_cli/ts_demuxer/ts_demux.py
hm3u8dl_cli-0.4.9.dist-info/METADATA
hm3u8dl_cli-0.4.9.dist-info/WHEEL
hm3u8dl_cli-0.4.9.dist-info/entry_points.txt
hm3u8dl_cli-0.4.9.dist-info/top_level.txt
hm3u8dl_cli-0.4.9.dist-info/RECORD
