Metadata-Version: 2.1
Name: hm3u8dl-cli
Version: 0.4.9
Summary: m3u8视频解析，下载，解密，合并的python程序，支持全平台
Home-page: https://github.com/hecoter/hm3u8dl_cli
Author: hecoter
Author-email: hecoter12138@gmail.com
Maintainer: hecoter
Maintainer-email: hecoter12138@gmail.com
License: MulanPSL2
Keywords: m3u8 AES decrypt download parse
Platform: all
Classifier: Development Status :: 4 - Beta
Classifier: Operating System :: OS Independent
Classifier: Intended Audience :: Developers
Classifier: Programming Language :: Python
Classifier: Programming Language :: Python :: 3.7
Classifier: Programming Language :: Python :: 3.8
Classifier: Programming Language :: Python :: 3.9
Classifier: Programming Language :: Python :: 3.10
Classifier: Programming Language :: Python :: 3.11
Classifier: Topic :: Software Development :: Libraries
Requires-Dist: m3u8
Requires-Dist: pycryptodome
Requires-Dist: tqdm
Requires-Dist: retry
Requires-Dist: tornado
Requires-Dist: rich
Requires-Dist: requests
Requires-Dist: multiprocess
